AgLight/AgLight.py
AgLight/__init__.py
aglight-0.1.0.dist-info/licenses/LICENSE
aglight-0.1.0.dist-info/METADATA
aglight-0.1.0.dist-info/WHEEL
aglight-0.1.0.dist-info/top_level.txt
aglight-0.1.0.dist-info/RECORD
