Metadata-Version: 2.4
Name: AgLight
Version: 0.1.0
Summary: Ultra-accelerating decorator for scientific and numerical Python functions.
Author: AG
Classifier: Programming Language :: Python :: 3
Classifier: License :: OSI Approved :: MIT License
Classifier: Operating System :: OS Independent
Requires-Python: >=3.7
License-File: LICENSE
Requires-Dist: numpy
Provides-Extra: numba
Requires-Dist: numba; extra == "numba"
Dynamic: author
Dynamic: classifier
Dynamic: description
Dynamic: description-content-type
Dynamic: license-file
Dynamic: provides-extra
Dynamic: requires-dist
Dynamic: requires-python
Dynamic: summary
